[
    {
        "Sender": "User50",
        "idNotify": "Notify0Message",
        "Cat": "Message",
        "Text": "New Message"
    },
    {
        "Sender": "User0",
        "idNotify": "Notify1Request",
        "Cat": "Request",
        "Text": "New Request"
    },
    {
        "Sender": "User8",
        "idNotify": "Notify2Request",
        "Cat": "Request",
        "Text": "New Request"
    },
    {
        "Sender": "User23",
        "idNotify": "Notify3Request",
        "Cat": "Request",
        "Text": "New Request"
    },
    {
        "Sender": "User75",
        "idNotify": "Notify4Message",
        "Cat": "Message",
        "Text": "New Message"
    },
    {
        "Sender": "User28",
        "idNotify": "Notify5Snap",
        "Cat": "Snap",
        "Text": "New Snap"
    },
    {
        "Sender": "User42",
        "idNotify": "Notify6Snap",
        "Cat": "Snap",
        "Text": "New Snap"
    },
    {
        "Sender": "User61",
        "idNotify": "Notify7Snap",
        "Cat": "Snap",
        "Text": "New Snap"
    },
    {
        "Sender": "User54",
        "idNotify": "Notify8Message",
        "Cat": "Message",
        "Text": "New Message"
    },
    {
        "Sender": "User22",
        "idNotify": "Notify0Snap",
        "Cat": "Snap",
        "Text": "New Snap"
    },
    {
        "Sender": "User85",
        "idNotify": "Notify1Message",
        "Cat": "Message",
        "Text": "New Message"
    },
    {
        "Sender": "User60",
        "idNotify": "Notify2Snap",
        "Cat": "Snap",
        "Text": "New Snap"
    },
    {
        "Sender": "User79",
        "idNotify": "Notify3Message",
        "Cat": "Message",
        "Text": "New Message"
    },
    {
        "Sender": "User84",
        "idNotify": "Notify4Snap",
        "Cat": "Snap",
        "Text": "New Snap"
    },
    {
        "Sender": "User5",
        "idNotify": "Notify5Snap",
        "Cat": "Snap",
        "Text": "New Snap"
    },
    {
        "Sender": "User19",
        "idNotify": "Notify6Request",
        "Cat": "Request",
        "Text": "New Request"
    },
    {
        "Sender": "User78",
        "idNotify": "Notify0Snap",
        "Cat": "Snap",
        "Text": "New Snap"
    },
    {
        "Sender": "User18",
        "idNotify": "Notify1Message",
        "Cat": "Message",
        "Text": "New Message"
    },
    {
        "Sender": "User74",
        "idNotify": "Notify2Message",
        "Cat": "Message",
        "Text": "New Message"
    },
    {
        "Sender": "User60",
        "idNotify": "Notify3Request",
        "Cat": "Request",
        "Text": "New Request"
    },
    {
        "Sender": "User18",
        "idNotify": "Notify4Message",
        "Cat": "Message",
        "Text": "New Message"
    },
    {
        "Sender": "User5",
        "idNotify": "Notify5Snap",
        "Cat": "Snap",
        "Text": "New Snap"
    },
    {
        "Sender": "User50",
        "idNotify": "Notify6Snap",
        "Cat": "Snap",
        "Text": "New Snap"
    },
    {
        "Sender": "User93",
        "idNotify": "Notify7Message",
        "Cat": "Message",
        "Text": "New Message"
    },
    {
        "Sender": "User71",
        "idNotify": "Notify0Snap",
        "Cat": "Snap",
        "Text": "New Snap"
    },
    {
        "Sender": "User11",
        "idNotify": "Notify1Request",
        "Cat": "Request",
        "Text": "New Request"
    },
    {
        "Sender": "User2",
        "idNotify": "Notify2Request",
        "Cat": "Request",
        "Text": "New Request"
    },
    {
        "Sender": "User82",
        "idNotify": "Notify0Snap",
        "Cat": "Snap",
        "Text": "New Snap"
    },
    {
        "Sender": "User93",
        "idNotify": "Notify1Message",
        "Cat": "Message",
        "Text": "New Message"
    },
    {
        "Sender": "User77",
        "idNotify": "Notify2Snap",
        "Cat": "Snap",
        "Text": "New Snap"
    },
    {
        "Sender": "User81",
        "idNotify": "Notify3Snap",
        "Cat": "Snap",
        "Text": "New Snap"
    },
    {
        "Sender": "User96",
        "idNotify": "Notify4Message",
        "Cat": "Message",
        "Text": "New Message"
    },
    {
        "Sender": "User24",
        "idNotify": "Notify5Message",
        "Cat": "Message",
        "Text": "New Message"
    },
    {
        "Sender": "User70",
        "idNotify": "Notify6Request",
        "Cat": "Request",
        "Text": "New Request"
    },
    {
        "Sender": "User70",
        "idNotify": "Notify7Snap",
        "Cat": "Snap",
        "Text": "New Snap"
    },
    {
        "Sender": "User57",
        "idNotify": "Notify0Message",
        "Cat": "Message",
        "Text": "New Message"
    },
    {
        "Sender": "User97",
        "idNotify": "Notify1Request",
        "Cat": "Request",
        "Text": "New Request"
    },
    {
        "Sender": "User17",
        "idNotify": "Notify2Message",
        "Cat": "Message",
        "Text": "New Message"
    },
    {
        "Sender": "User67",
        "idNotify": "Notify3Snap",
        "Cat": "Snap",
        "Text": "New Snap"
    },
    {
        "Sender": "User88",
        "idNotify": "Notify4Message",
        "Cat": "Message",
        "Text": "New Message"
    },
    {
        "Sender": "User36",
        "idNotify": "Notify5Message",
        "Cat": "Message",
        "Text": "New Message"
    },
    {
        "Sender": "User79",
        "idNotify": "Notify6Snap",
        "Cat": "Snap",
        "Text": "New Snap"
    },
    {
        "Sender": "User20",
        "idNotify": "Notify7Snap",
        "Cat": "Snap",
        "Text": "New Snap"
    },
    {
        "Sender": "User13",
        "idNotify": "Notify8Message",
        "Cat": "Message",
        "Text": "New Message"
    },
    {
        "Sender": "User93",
        "idNotify": "Notify0Snap",
        "Cat": "Snap",
        "Text": "New Snap"
    },
    {
        "Sender": "User2",
        "idNotify": "Notify1Snap",
        "Cat": "Snap",
        "Text": "New Snap"
    },
    {
        "Sender": "User66",
        "idNotify": "Notify2Snap",
        "Cat": "Snap",
        "Text": "New Snap"
    },
    {
        "Sender": "User31",
        "idNotify": "Notify3Request",
        "Cat": "Request",
        "Text": "New Request"
    },
    {
        "Sender": "User39",
        "idNotify": "Notify4Message",
        "Cat": "Message",
        "Text": "New Message"
    },
    {
        "Sender": "User75",
        "idNotify": "Notify5Snap",
        "Cat": "Snap",
        "Text": "New Snap"
    },
    {
        "Sender": "User83",
        "idNotify": "Notify6Message",
        "Cat": "Message",
        "Text": "New Message"
    },
    {
        "Sender": "User50",
        "idNotify": "Notify7Snap",
        "Cat": "Snap",
        "Text": "New Snap"
    },
    {
        "Sender": "User81",
        "idNotify": "Notify0Snap",
        "Cat": "Snap",
        "Text": "New Snap"
    },
    {
        "Sender": "User99",
        "idNotify": "Notify1Request",
        "Cat": "Request",
        "Text": "New Request"
    },
    {
        "Sender": "User31",
        "idNotify": "Notify2Message",
        "Cat": "Message",
        "Text": "New Message"
    },
    {
        "Sender": "User83",
        "idNotify": "Notify3Snap",
        "Cat": "Snap",
        "Text": "New Snap"
    },
    {
        "Sender": "User1",
        "idNotify": "Notify4Snap",
        "Cat": "Snap",
        "Text": "New Snap"
    },
    {
        "Sender": "User91",
        "idNotify": "Notify5Request",
        "Cat": "Request",
        "Text": "New Request"
    },
    {
        "Sender": "User95",
        "idNotify": "Notify6Snap",
        "Cat": "Snap",
        "Text": "New Snap"
    },
    {
        "Sender": "User81",
        "idNotify": "Notify0Request",
        "Cat": "Request",
        "Text": "New Request"
    },
    {
        "Sender": "User9",
        "idNotify": "Notify1Message",
        "Cat": "Message",
        "Text": "New Message"
    },
    {
        "Sender": "User4",
        "idNotify": "Notify2Snap",
        "Cat": "Snap",
        "Text": "New Snap"
    },
    {
        "Sender": "User65",
        "idNotify": "Notify3Request",
        "Cat": "Request",
        "Text": "New Request"
    },
    {
        "Sender": "User27",
        "idNotify": "Notify4Message",
        "Cat": "Message",
        "Text": "New Message"
    },
    {
        "Sender": "User76",
        "idNotify": "Notify5Request",
        "Cat": "Request",
        "Text": "New Request"
    },
    {
        "Sender": "User91",
        "idNotify": "Notify0Request",
        "Cat": "Request",
        "Text": "New Request"
    },
    {
        "Sender": "User91",
        "idNotify": "Notify1Snap",
        "Cat": "Snap",
        "Text": "New Snap"
    },
    {
        "Sender": "User35",
        "idNotify": "Notify2Snap",
        "Cat": "Snap",
        "Text": "New Snap"
    },
    {
        "Sender": "User33",
        "idNotify": "Notify3Message",
        "Cat": "Message",
        "Text": "New Message"
    },
    {
        "Sender": "User87",
        "idNotify": "Notify4Snap",
        "Cat": "Snap",
        "Text": "New Snap"
    },
    {
        "Sender": "User98",
        "idNotify": "Notify5Snap",
        "Cat": "Snap",
        "Text": "New Snap"
    },
    {
        "Sender": "User4",
        "idNotify": "Notify6Message",
        "Cat": "Message",
        "Text": "New Message"
    },
    {
        "Sender": "User1",
        "idNotify": "Notify7Message",
        "Cat": "Message",
        "Text": "New Message"
    },
    {
        "Sender": "User37",
        "idNotify": "Notify0Request",
        "Cat": "Request",
        "Text": "New Request"
    },
    {
        "Sender": "User13",
        "idNotify": "Notify1Message",
        "Cat": "Message",
        "Text": "New Message"
    },
    {
        "Sender": "User27",
        "idNotify": "Notify2Message",
        "Cat": "Message",
        "Text": "New Message"
    },
    {
        "Sender": "User14",
        "idNotify": "Notify3Request",
        "Cat": "Request",
        "Text": "New Request"
    },
    {
        "Sender": "User75",
        "idNotify": "Notify4Message",
        "Cat": "Message",
        "Text": "New Message"
    },
    {
        "Sender": "User13",
        "idNotify": "Notify5Message",
        "Cat": "Message",
        "Text": "New Message"
    },
    {
        "Sender": "User95",
        "idNotify": "Notify6Request",
        "Cat": "Request",
        "Text": "New Request"
    },
    {
        "Sender": "User42",
        "idNotify": "Notify7Message",
        "Cat": "Message",
        "Text": "New Message"
    },
    {
        "Sender": "User85",
        "idNotify": "Notify8Message",
        "Cat": "Message",
        "Text": "New Message"
    },
    {
        "Sender": "User38",
        "idNotify": "Notify9Request",
        "Cat": "Request",
        "Text": "New Request"
    },
    {
        "Sender": "User92",
        "idNotify": "Notify0Message",
        "Cat": "Message",
        "Text": "New Message"
    },
    {
        "Sender": "User80",
        "idNotify": "Notify1Request",
        "Cat": "Request",
        "Text": "New Request"
    },
    {
        "Sender": "User0",
        "idNotify": "Notify2Snap",
        "Cat": "Snap",
        "Text": "New Snap"
    },
    {
        "Sender": "User50",
        "idNotify": "Notify3Snap",
        "Cat": "Snap",
        "Text": "New Snap"
    },
    {
        "Sender": "User1",
        "idNotify": "Notify4Message",
        "Cat": "Message",
        "Text": "New Message"
    },
    {
        "Sender": "User56",
        "idNotify": "Notify5Message",
        "Cat": "Message",
        "Text": "New Message"
    },
    {
        "Sender": "User71",
        "idNotify": "Notify6Message",
        "Cat": "Message",
        "Text": "New Message"
    },
    {
        "Sender": "User89",
        "idNotify": "Notify7Message",
        "Cat": "Message",
        "Text": "New Message"
    },
    {
        "Sender": "User73",
        "idNotify": "Notify0Request",
        "Cat": "Request",
        "Text": "New Request"
    },
    {
        "Sender": "User54",
        "idNotify": "Notify1Snap",
        "Cat": "Snap",
        "Text": "New Snap"
    },
    {
        "Sender": "User70",
        "idNotify": "Notify2Message",
        "Cat": "Message",
        "Text": "New Message"
    },
    {
        "Sender": "User33",
        "idNotify": "Notify3Snap",
        "Cat": "Snap",
        "Text": "New Snap"
    },
    {
        "Sender": "User53",
        "idNotify": "Notify4Snap",
        "Cat": "Snap",
        "Text": "New Snap"
    },
    {
        "Sender": "User10",
        "idNotify": "Notify5Snap",
        "Cat": "Snap",
        "Text": "New Snap"
    },
    {
        "Sender": "User74",
        "idNotify": "Notify0Snap",
        "Cat": "Snap",
        "Text": "New Snap"
    },
    {
        "Sender": "User23",
        "idNotify": "Notify1Message",
        "Cat": "Message",
        "Text": "New Message"
    },
    {
        "Sender": "User17",
        "idNotify": "Notify0Request",
        "Cat": "Request",
        "Text": "New Request"
    },
    {
        "Sender": "User23",
        "idNotify": "Notify1Message",
        "Cat": "Message",
        "Text": "New Message"
    },
    {
        "Sender": "User79",
        "idNotify": "Notify2Snap",
        "Cat": "Snap",
        "Text": "New Snap"
    },
    {
        "Sender": "User54",
        "idNotify": "Notify3Snap",
        "Cat": "Snap",
        "Text": "New Snap"
    },
    {
        "Sender": "User21",
        "idNotify": "Notify4Request",
        "Cat": "Request",
        "Text": "New Request"
    },
    {
        "Sender": "User60",
        "idNotify": "Notify5Message",
        "Cat": "Message",
        "Text": "New Message"
    },
    {
        "Sender": "User47",
        "idNotify": "Notify6Message",
        "Cat": "Message",
        "Text": "New Message"
    },
    {
        "Sender": "User4",
        "idNotify": "Notify7Message",
        "Cat": "Message",
        "Text": "New Message"
    },
    {
        "Sender": "User41",
        "idNotify": "Notify8Snap",
        "Cat": "Snap",
        "Text": "New Snap"
    },
    {
        "Sender": "User93",
        "idNotify": "Notify0Request",
        "Cat": "Request",
        "Text": "New Request"
    },
    {
        "Sender": "User45",
        "idNotify": "Notify1Snap",
        "Cat": "Snap",
        "Text": "New Snap"
    },
    {
        "Sender": "User79",
        "idNotify": "Notify2Snap",
        "Cat": "Snap",
        "Text": "New Snap"
    },
    {
        "Sender": "User98",
        "idNotify": "Notify3Snap",
        "Cat": "Snap",
        "Text": "New Snap"
    },
    {
        "Sender": "User87",
        "idNotify": "Notify4Message",
        "Cat": "Message",
        "Text": "New Message"
    },
    {
        "Sender": "User25",
        "idNotify": "Notify0Snap",
        "Cat": "Snap",
        "Text": "New Snap"
    },
    {
        "Sender": "User75",
        "idNotify": "Notify1Request",
        "Cat": "Request",
        "Text": "New Request"
    },
    {
        "Sender": "User98",
        "idNotify": "Notify2Snap",
        "Cat": "Snap",
        "Text": "New Snap"
    },
    {
        "Sender": "User96",
        "idNotify": "Notify3Request",
        "Cat": "Request",
        "Text": "New Request"
    },
    {
        "Sender": "User33",
        "idNotify": "Notify4Snap",
        "Cat": "Snap",
        "Text": "New Snap"
    },
    {
        "Sender": "User44",
        "idNotify": "Notify5Snap",
        "Cat": "Snap",
        "Text": "New Snap"
    },
    {
        "Sender": "User29",
        "idNotify": "Notify0Snap",
        "Cat": "Snap",
        "Text": "New Snap"
    },
    {
        "Sender": "User72",
        "idNotify": "Notify1Request",
        "Cat": "Request",
        "Text": "New Request"
    },
    {
        "Sender": "User90",
        "idNotify": "Notify2Snap",
        "Cat": "Snap",
        "Text": "New Snap"
    },
    {
        "Sender": "User51",
        "idNotify": "Notify3Request",
        "Cat": "Request",
        "Text": "New Request"
    },
    {
        "Sender": "User98",
        "idNotify": "Notify4Message",
        "Cat": "Message",
        "Text": "New Message"
    },
    {
        "Sender": "User5",
        "idNotify": "Notify5Snap",
        "Cat": "Snap",
        "Text": "New Snap"
    },
    {
        "Sender": "User5",
        "idNotify": "Notify6Message",
        "Cat": "Message",
        "Text": "New Message"
    },
    {
        "Sender": "User24",
        "idNotify": "Notify7Snap",
        "Cat": "Snap",
        "Text": "New Snap"
    },
    {
        "Sender": "User23",
        "idNotify": "Notify0Message",
        "Cat": "Message",
        "Text": "New Message"
    },
    {
        "Sender": "User13",
        "idNotify": "Notify1Message",
        "Cat": "Message",
        "Text": "New Message"
    },
    {
        "Sender": "User30",
        "idNotify": "Notify2Message",
        "Cat": "Message",
        "Text": "New Message"
    },
    {
        "Sender": "User74",
        "idNotify": "Notify3Snap",
        "Cat": "Snap",
        "Text": "New Snap"
    },
    {
        "Sender": "User18",
        "idNotify": "Notify4Snap",
        "Cat": "Snap",
        "Text": "New Snap"
    },
    {
        "Sender": "User57",
        "idNotify": "Notify0Message",
        "Cat": "Message",
        "Text": "New Message"
    },
    {
        "Sender": "User39",
        "idNotify": "Notify1Request",
        "Cat": "Request",
        "Text": "New Request"
    },
    {
        "Sender": "User72",
        "idNotify": "Notify2Request",
        "Cat": "Request",
        "Text": "New Request"
    },
    {
        "Sender": "User89",
        "idNotify": "Notify3Snap",
        "Cat": "Snap",
        "Text": "New Snap"
    },
    {
        "Sender": "User71",
        "idNotify": "Notify4Message",
        "Cat": "Message",
        "Text": "New Message"
    },
    {
        "Sender": "User93",
        "idNotify": "Notify5Request",
        "Cat": "Request",
        "Text": "New Request"
    },
    {
        "Sender": "User26",
        "idNotify": "Notify6Message",
        "Cat": "Message",
        "Text": "New Message"
    },
    {
        "Sender": "User20",
        "idNotify": "Notify7Request",
        "Cat": "Request",
        "Text": "New Request"
    },
    {
        "Sender": "User85",
        "idNotify": "Notify8Snap",
        "Cat": "Snap",
        "Text": "New Snap"
    },
    {
        "Sender": "User56",
        "idNotify": "Notify9Request",
        "Cat": "Request",
        "Text": "New Request"
    },
    {
        "Sender": "User5",
        "idNotify": "Notify0Message",
        "Cat": "Message",
        "Text": "New Message"
    },
    {
        "Sender": "User26",
        "idNotify": "Notify1Message",
        "Cat": "Message",
        "Text": "New Message"
    },
    {
        "Sender": "User66",
        "idNotify": "Notify2Snap",
        "Cat": "Snap",
        "Text": "New Snap"
    },
    {
        "Sender": "User41",
        "idNotify": "Notify3Message",
        "Cat": "Message",
        "Text": "New Message"
    },
    {
        "Sender": "User39",
        "idNotify": "Notify4Snap",
        "Cat": "Snap",
        "Text": "New Snap"
    },
    {
        "Sender": "User56",
        "idNotify": "Notify5Snap",
        "Cat": "Snap",
        "Text": "New Snap"
    },
    {
        "Sender": "User21",
        "idNotify": "Notify6Request",
        "Cat": "Request",
        "Text": "New Request"
    },
    {
        "Sender": "User38",
        "idNotify": "Notify7Snap",
        "Cat": "Snap",
        "Text": "New Snap"
    },
    {
        "Sender": "User25",
        "idNotify": "Notify0Request",
        "Cat": "Request",
        "Text": "New Request"
    },
    {
        "Sender": "User61",
        "idNotify": "Notify1Request",
        "Cat": "Request",
        "Text": "New Request"
    },
    {
        "Sender": "User7",
        "idNotify": "Notify2Request",
        "Cat": "Request",
        "Text": "New Request"
    },
    {
        "Sender": "User11",
        "idNotify": "Notify3Snap",
        "Cat": "Snap",
        "Text": "New Snap"
    },
    {
        "Sender": "User63",
        "idNotify": "Notify4Snap",
        "Cat": "Snap",
        "Text": "New Snap"
    },
    {
        "Sender": "User34",
        "idNotify": "Notify5Request",
        "Cat": "Request",
        "Text": "New Request"
    },
    {
        "Sender": "User93",
        "idNotify": "Notify6Request",
        "Cat": "Request",
        "Text": "New Request"
    },
    {
        "Sender": "User65",
        "idNotify": "Notify7Message",
        "Cat": "Message",
        "Text": "New Message"
    },
    {
        "Sender": "User26",
        "idNotify": "Notify0Message",
        "Cat": "Message",
        "Text": "New Message"
    },
    {
        "Sender": "User54",
        "idNotify": "Notify1Request",
        "Cat": "Request",
        "Text": "New Request"
    },
    {
        "Sender": "User88",
        "idNotify": "Notify2Message",
        "Cat": "Message",
        "Text": "New Message"
    },
    {
        "Sender": "User58",
        "idNotify": "Notify3Message",
        "Cat": "Message",
        "Text": "New Message"
    },
    {
        "Sender": "User12",
        "idNotify": "Notify4Request",
        "Cat": "Request",
        "Text": "New Request"
    },
    {
        "Sender": "User26",
        "idNotify": "Notify5Snap",
        "Cat": "Snap",
        "Text": "New Snap"
    },
    {
        "Sender": "User16",
        "idNotify": "Notify6Request",
        "Cat": "Request",
        "Text": "New Request"
    },
    {
        "Sender": "User21",
        "idNotify": "Notify7Message",
        "Cat": "Message",
        "Text": "New Message"
    },
    {
        "Sender": "User88",
        "idNotify": "Notify8Message",
        "Cat": "Message",
        "Text": "New Message"
    },
    {
        "Sender": "User34",
        "idNotify": "Notify9Snap",
        "Cat": "Snap",
        "Text": "New Snap"
    },
    {
        "Sender": "User2",
        "idNotify": "Notify0Snap",
        "Cat": "Snap",
        "Text": "New Snap"
    },
    {
        "Sender": "User86",
        "idNotify": "Notify1Request",
        "Cat": "Request",
        "Text": "New Request"
    },
    {
        "Sender": "User98",
        "idNotify": "Notify2Snap",
        "Cat": "Snap",
        "Text": "New Snap"
    },
    {
        "Sender": "User99",
        "idNotify": "Notify3Request",
        "Cat": "Request",
        "Text": "New Request"
    },
    {
        "Sender": "User26",
        "idNotify": "Notify4Request",
        "Cat": "Request",
        "Text": "New Request"
    },
    {
        "Sender": "User55",
        "idNotify": "Notify5Request",
        "Cat": "Request",
        "Text": "New Request"
    },
    {
        "Sender": "User70",
        "idNotify": "Notify6Request",
        "Cat": "Request",
        "Text": "New Request"
    },
    {
        "Sender": "User99",
        "idNotify": "Notify0Request",
        "Cat": "Request",
        "Text": "New Request"
    },
    {
        "Sender": "User27",
        "idNotify": "Notify1Request",
        "Cat": "Request",
        "Text": "New Request"
    },
    {
        "Sender": "User91",
        "idNotify": "Notify2Snap",
        "Cat": "Snap",
        "Text": "New Snap"
    },
    {
        "Sender": "User34",
        "idNotify": "Notify3Snap",
        "Cat": "Snap",
        "Text": "New Snap"
    },
    {
        "Sender": "User59",
        "idNotify": "Notify4Request",
        "Cat": "Request",
        "Text": "New Request"
    },
    {
        "Sender": "User51",
        "idNotify": "Notify5Snap",
        "Cat": "Snap",
        "Text": "New Snap"
    },
    {
        "Sender": "User6",
        "idNotify": "Notify6Request",
        "Cat": "Request",
        "Text": "New Request"
    },
    {
        "Sender": "User20",
        "idNotify": "Notify7Snap",
        "Cat": "Snap",
        "Text": "New Snap"
    },
    {
        "Sender": "User0",
        "idNotify": "Notify0Request",
        "Cat": "Request",
        "Text": "New Request"
    },
    {
        "Sender": "User57",
        "idNotify": "Notify1Request",
        "Cat": "Request",
        "Text": "New Request"
    },
    {
        "Sender": "User1",
        "idNotify": "Notify2Request",
        "Cat": "Request",
        "Text": "New Request"
    },
    {
        "Sender": "User1",
        "idNotify": "Notify3Snap",
        "Cat": "Snap",
        "Text": "New Snap"
    },
    {
        "Sender": "User98",
        "idNotify": "Notify4Snap",
        "Cat": "Snap",
        "Text": "New Snap"
    },
    {
        "Sender": "User18",
        "idNotify": "Notify5Message",
        "Cat": "Message",
        "Text": "New Message"
    },
    {
        "Sender": "User81",
        "idNotify": "Notify6Snap",
        "Cat": "Snap",
        "Text": "New Snap"
    },
    {
        "Sender": "User58",
        "idNotify": "Notify7Message",
        "Cat": "Message",
        "Text": "New Message"
    },
    {
        "Sender": "User34",
        "idNotify": "Notify8Snap",
        "Cat": "Snap",
        "Text": "New Snap"
    },
    {
        "Sender": "User46",
        "idNotify": "Notify9Request",
        "Cat": "Request",
        "Text": "New Request"
    },
    {
        "Sender": "User85",
        "idNotify": "Notify0Message",
        "Cat": "Message",
        "Text": "New Message"
    },
    {
        "Sender": "User42",
        "idNotify": "Notify1Snap",
        "Cat": "Snap",
        "Text": "New Snap"
    },
    {
        "Sender": "User52",
        "idNotify": "Notify2Request",
        "Cat": "Request",
        "Text": "New Request"
    },
    {
        "Sender": "User58",
        "idNotify": "Notify3Request",
        "Cat": "Request",
        "Text": "New Request"
    },
    {
        "Sender": "User93",
        "idNotify": "Notify4Message",
        "Cat": "Message",
        "Text": "New Message"
    },
    {
        "Sender": "User10",
        "idNotify": "Notify5Request",
        "Cat": "Request",
        "Text": "New Request"
    },
    {
        "Sender": "User51",
        "idNotify": "Notify6Request",
        "Cat": "Request",
        "Text": "New Request"
    },
    {
        "Sender": "User41",
        "idNotify": "Notify7Request",
        "Cat": "Request",
        "Text": "New Request"
    },
    {
        "Sender": "User51",
        "idNotify": "Notify0Snap",
        "Cat": "Snap",
        "Text": "New Snap"
    },
    {
        "Sender": "User87",
        "idNotify": "Notify1Snap",
        "Cat": "Snap",
        "Text": "New Snap"
    },
    {
        "Sender": "User98",
        "idNotify": "Notify2Request",
        "Cat": "Request",
        "Text": "New Request"
    },
    {
        "Sender": "User45",
        "idNotify": "Notify3Snap",
        "Cat": "Snap",
        "Text": "New Snap"
    },
    {
        "Sender": "User37",
        "idNotify": "Notify4Message",
        "Cat": "Message",
        "Text": "New Message"
    },
    {
        "Sender": "User91",
        "idNotify": "Notify5Snap",
        "Cat": "Snap",
        "Text": "New Snap"
    },
    {
        "Sender": "User34",
        "idNotify": "Notify6Message",
        "Cat": "Message",
        "Text": "New Message"
    },
    {
        "Sender": "User13",
        "idNotify": "Notify7Request",
        "Cat": "Request",
        "Text": "New Request"
    },
    {
        "Sender": "User36",
        "idNotify": "Notify0Message",
        "Cat": "Message",
        "Text": "New Message"
    },
    {
        "Sender": "User89",
        "idNotify": "Notify1Snap",
        "Cat": "Snap",
        "Text": "New Snap"
    },
    {
        "Sender": "User6",
        "idNotify": "Notify2Request",
        "Cat": "Request",
        "Text": "New Request"
    },
    {
        "Sender": "User95",
        "idNotify": "Notify3Snap",
        "Cat": "Snap",
        "Text": "New Snap"
    },
    {
        "Sender": "User56",
        "idNotify": "Notify4Snap",
        "Cat": "Snap",
        "Text": "New Snap"
    },
    {
        "Sender": "User83",
        "idNotify": "Notify5Request",
        "Cat": "Request",
        "Text": "New Request"
    },
    {
        "Sender": "User14",
        "idNotify": "Notify6Snap",
        "Cat": "Snap",
        "Text": "New Snap"
    },
    {
        "Sender": "User8",
        "idNotify": "Notify7Message",
        "Cat": "Message",
        "Text": "New Message"
    },
    {
        "Sender": "User21",
        "idNotify": "Notify8Snap",
        "Cat": "Snap",
        "Text": "New Snap"
    },
    {
        "Sender": "User48",
        "idNotify": "Notify0Message",
        "Cat": "Message",
        "Text": "New Message"
    },
    {
        "Sender": "User58",
        "idNotify": "Notify1Snap",
        "Cat": "Snap",
        "Text": "New Snap"
    },
    {
        "Sender": "User19",
        "idNotify": "Notify2Snap",
        "Cat": "Snap",
        "Text": "New Snap"
    },
    {
        "Sender": "User77",
        "idNotify": "Notify3Request",
        "Cat": "Request",
        "Text": "New Request"
    },
    {
        "Sender": "User22",
        "idNotify": "Notify4Message",
        "Cat": "Message",
        "Text": "New Message"
    },
    {
        "Sender": "User64",
        "idNotify": "Notify5Snap",
        "Cat": "Snap",
        "Text": "New Snap"
    },
    {
        "Sender": "User85",
        "idNotify": "Notify6Snap",
        "Cat": "Snap",
        "Text": "New Snap"
    },
    {
        "Sender": "User54",
        "idNotify": "Notify0Message",
        "Cat": "Message",
        "Text": "New Message"
    },
    {
        "Sender": "User23",
        "idNotify": "Notify1Request",
        "Cat": "Request",
        "Text": "New Request"
    },
    {
        "Sender": "User30",
        "idNotify": "Notify2Message",
        "Cat": "Message",
        "Text": "New Message"
    },
    {
        "Sender": "User64",
        "idNotify": "Notify3Snap",
        "Cat": "Snap",
        "Text": "New Snap"
    },
    {
        "Sender": "User47",
        "idNotify": "Notify4Request",
        "Cat": "Request",
        "Text": "New Request"
    },
    {
        "Sender": "User6",
        "idNotify": "Notify5Snap",
        "Cat": "Snap",
        "Text": "New Snap"
    },
    {
        "Sender": "User72",
        "idNotify": "Notify6Message",
        "Cat": "Message",
        "Text": "New Message"
    },
    {
        "Sender": "User33",
        "idNotify": "Notify7Message",
        "Cat": "Message",
        "Text": "New Message"
    },
    {
        "Sender": "User24",
        "idNotify": "Notify0Request",
        "Cat": "Request",
        "Text": "New Request"
    },
    {
        "Sender": "User62",
        "idNotify": "Notify1Request",
        "Cat": "Request",
        "Text": "New Request"
    },
    {
        "Sender": "User1",
        "idNotify": "Notify2Request",
        "Cat": "Request",
        "Text": "New Request"
    },
    {
        "Sender": "User41",
        "idNotify": "Notify3Message",
        "Cat": "Message",
        "Text": "New Message"
    },
    {
        "Sender": "User15",
        "idNotify": "Notify4Snap",
        "Cat": "Snap",
        "Text": "New Snap"
    },
    {
        "Sender": "User50",
        "idNotify": "Notify5Request",
        "Cat": "Request",
        "Text": "New Request"
    },
    {
        "Sender": "User90",
        "idNotify": "Notify6Request",
        "Cat": "Request",
        "Text": "New Request"
    },
    {
        "Sender": "User96",
        "idNotify": "Notify7Message",
        "Cat": "Message",
        "Text": "New Message"
    },
    {
        "Sender": "User54",
        "idNotify": "Notify8Snap",
        "Cat": "Snap",
        "Text": "New Snap"
    },
    {
        "Sender": "User72",
        "idNotify": "Notify0Request",
        "Cat": "Request",
        "Text": "New Request"
    },
    {
        "Sender": "User82",
        "idNotify": "Notify1Request",
        "Cat": "Request",
        "Text": "New Request"
    },
    {
        "Sender": "User19",
        "idNotify": "Notify2Message",
        "Cat": "Message",
        "Text": "New Message"
    },
    {
        "Sender": "User24",
        "idNotify": "Notify3Snap",
        "Cat": "Snap",
        "Text": "New Snap"
    },
    {
        "Sender": "User90",
        "idNotify": "Notify4Snap",
        "Cat": "Snap",
        "Text": "New Snap"
    },
    {
        "Sender": "User30",
        "idNotify": "Notify5Message",
        "Cat": "Message",
        "Text": "New Message"
    },
    {
        "Sender": "User46",
        "idNotify": "Notify0Snap",
        "Cat": "Snap",
        "Text": "New Snap"
    },
    {
        "Sender": "User62",
        "idNotify": "Notify1Snap",
        "Cat": "Snap",
        "Text": "New Snap"
    },
    {
        "Sender": "User78",
        "idNotify": "Notify0Message",
        "Cat": "Message",
        "Text": "New Message"
    },
    {
        "Sender": "User70",
        "idNotify": "Notify0Message",
        "Cat": "Message",
        "Text": "New Message"
    },
    {
        "Sender": "User45",
        "idNotify": "Notify1Snap",
        "Cat": "Snap",
        "Text": "New Snap"
    },
    {
        "Sender": "User34",
        "idNotify": "Notify2Message",
        "Cat": "Message",
        "Text": "New Message"
    },
    {
        "Sender": "User37",
        "idNotify": "Notify0Request",
        "Cat": "Request",
        "Text": "New Request"
    },
    {
        "Sender": "User67",
        "idNotify": "Notify1Request",
        "Cat": "Request",
        "Text": "New Request"
    },
    {
        "Sender": "User5",
        "idNotify": "Notify2Message",
        "Cat": "Message",
        "Text": "New Message"
    },
    {
        "Sender": "User43",
        "idNotify": "Notify3Snap",
        "Cat": "Snap",
        "Text": "New Snap"
    },
    {
        "Sender": "User6",
        "idNotify": "Notify4Snap",
        "Cat": "Snap",
        "Text": "New Snap"
    },
    {
        "Sender": "User15",
        "idNotify": "Notify5Request",
        "Cat": "Request",
        "Text": "New Request"
    },
    {
        "Sender": "User43",
        "idNotify": "Notify0Message",
        "Cat": "Message",
        "Text": "New Message"
    },
    {
        "Sender": "User3",
        "idNotify": "Notify1Request",
        "Cat": "Request",
        "Text": "New Request"
    },
    {
        "Sender": "User58",
        "idNotify": "Notify0Snap",
        "Cat": "Snap",
        "Text": "New Snap"
    },
    {
        "Sender": "User48",
        "idNotify": "Notify1Request",
        "Cat": "Request",
        "Text": "New Request"
    },
    {
        "Sender": "User30",
        "idNotify": "Notify2Message",
        "Cat": "Message",
        "Text": "New Message"
    },
    {
        "Sender": "User41",
        "idNotify": "Notify0Request",
        "Cat": "Request",
        "Text": "New Request"
    },
    {
        "Sender": "User82",
        "idNotify": "Notify1Snap",
        "Cat": "Snap",
        "Text": "New Snap"
    },
    {
        "Sender": "User1",
        "idNotify": "Notify2Request",
        "Cat": "Request",
        "Text": "New Request"
    },
    {
        "Sender": "User54",
        "idNotify": "Notify3Snap",
        "Cat": "Snap",
        "Text": "New Snap"
    },
    {
        "Sender": "User25",
        "idNotify": "Notify4Request",
        "Cat": "Request",
        "Text": "New Request"
    },
    {
        "Sender": "User66",
        "idNotify": "Notify5Request",
        "Cat": "Request",
        "Text": "New Request"
    },
    {
        "Sender": "User90",
        "idNotify": "Notify6Snap",
        "Cat": "Snap",
        "Text": "New Snap"
    },
    {
        "Sender": "User4",
        "idNotify": "Notify0Snap",
        "Cat": "Snap",
        "Text": "New Snap"
    },
    {
        "Sender": "User64",
        "idNotify": "Notify1Snap",
        "Cat": "Snap",
        "Text": "New Snap"
    },
    {
        "Sender": "User70",
        "idNotify": "Notify0Snap",
        "Cat": "Snap",
        "Text": "New Snap"
    },
    {
        "Sender": "User18",
        "idNotify": "Notify1Message",
        "Cat": "Message",
        "Text": "New Message"
    },
    {
        "Sender": "User57",
        "idNotify": "Notify0Message",
        "Cat": "Message",
        "Text": "New Message"
    },
    {
        "Sender": "User17",
        "idNotify": "Notify1Request",
        "Cat": "Request",
        "Text": "New Request"
    },
    {
        "Sender": "User58",
        "idNotify": "Notify2Request",
        "Cat": "Request",
        "Text": "New Request"
    },
    {
        "Sender": "User87",
        "idNotify": "Notify3Message",
        "Cat": "Message",
        "Text": "New Message"
    },
    {
        "Sender": "User16",
        "idNotify": "Notify4Request",
        "Cat": "Request",
        "Text": "New Request"
    },
    {
        "Sender": "User30",
        "idNotify": "Notify5Snap",
        "Cat": "Snap",
        "Text": "New Snap"
    },
    {
        "Sender": "User58",
        "idNotify": "Notify6Snap",
        "Cat": "Snap",
        "Text": "New Snap"
    },
    {
        "Sender": "User73",
        "idNotify": "Notify7Snap",
        "Cat": "Snap",
        "Text": "New Snap"
    },
    {
        "Sender": "User90",
        "idNotify": "Notify8Request",
        "Cat": "Request",
        "Text": "New Request"
    },
    {
        "Sender": "User40",
        "idNotify": "Notify0Message",
        "Cat": "Message",
        "Text": "New Message"
    },
    {
        "Sender": "User56",
        "idNotify": "Notify1Snap",
        "Cat": "Snap",
        "Text": "New Snap"
    },
    {
        "Sender": "User64",
        "idNotify": "Notify2Snap",
        "Cat": "Snap",
        "Text": "New Snap"
    },
    {
        "Sender": "User6",
        "idNotify": "Notify3Request",
        "Cat": "Request",
        "Text": "New Request"
    },
    {
        "Sender": "User77",
        "idNotify": "Notify0Snap",
        "Cat": "Snap",
        "Text": "New Snap"
    },
    {
        "Sender": "User18",
        "idNotify": "Notify1Message",
        "Cat": "Message",
        "Text": "New Message"
    },
    {
        "Sender": "User77",
        "idNotify": "Notify2Snap",
        "Cat": "Snap",
        "Text": "New Snap"
    },
    {
        "Sender": "User53",
        "idNotify": "Notify3Message",
        "Cat": "Message",
        "Text": "New Message"
    },
    {
        "Sender": "User54",
        "idNotify": "Notify4Message",
        "Cat": "Message",
        "Text": "New Message"
    },
    {
        "Sender": "User33",
        "idNotify": "Notify5Snap",
        "Cat": "Snap",
        "Text": "New Snap"
    },
    {
        "Sender": "User88",
        "idNotify": "Notify6Request",
        "Cat": "Request",
        "Text": "New Request"
    },
    {
        "Sender": "User27",
        "idNotify": "Notify7Snap",
        "Cat": "Snap",
        "Text": "New Snap"
    },
    {
        "Sender": "User32",
        "idNotify": "Notify0Snap",
        "Cat": "Snap",
        "Text": "New Snap"
    },
    {
        "Sender": "User66",
        "idNotify": "Notify1Snap",
        "Cat": "Snap",
        "Text": "New Snap"
    },
    {
        "Sender": "User81",
        "idNotify": "Notify2Snap",
        "Cat": "Snap",
        "Text": "New Snap"
    },
    {
        "Sender": "User9",
        "idNotify": "Notify3Message",
        "Cat": "Message",
        "Text": "New Message"
    },
    {
        "Sender": "User54",
        "idNotify": "Notify4Snap",
        "Cat": "Snap",
        "Text": "New Snap"
    },
    {
        "Sender": "User65",
        "idNotify": "Notify5Request",
        "Cat": "Request",
        "Text": "New Request"
    },
    {
        "Sender": "User49",
        "idNotify": "Notify6Request",
        "Cat": "Request",
        "Text": "New Request"
    },
    {
        "Sender": "User38",
        "idNotify": "Notify0Snap",
        "Cat": "Snap",
        "Text": "New Snap"
    },
    {
        "Sender": "User56",
        "idNotify": "Notify1Request",
        "Cat": "Request",
        "Text": "New Request"
    },
    {
        "Sender": "User25",
        "idNotify": "Notify2Message",
        "Cat": "Message",
        "Text": "New Message"
    },
    {
        "Sender": "User5",
        "idNotify": "Notify3Request",
        "Cat": "Request",
        "Text": "New Request"
    },
    {
        "Sender": "User95",
        "idNotify": "Notify0Request",
        "Cat": "Request",
        "Text": "New Request"
    },
    {
        "Sender": "User62",
        "idNotify": "Notify1Message",
        "Cat": "Message",
        "Text": "New Message"
    },
    {
        "Sender": "User66",
        "idNotify": "Notify2Request",
        "Cat": "Request",
        "Text": "New Request"
    },
    {
        "Sender": "User73",
        "idNotify": "Notify3Message",
        "Cat": "Message",
        "Text": "New Message"
    },
    {
        "Sender": "User19",
        "idNotify": "Notify0Request",
        "Cat": "Request",
        "Text": "New Request"
    },
    {
        "Sender": "User5",
        "idNotify": "Notify0Request",
        "Cat": "Request",
        "Text": "New Request"
    },
    {
        "Sender": "User87",
        "idNotify": "Notify1Snap",
        "Cat": "Snap",
        "Text": "New Snap"
    },
    {
        "Sender": "User45",
        "idNotify": "Notify2Snap",
        "Cat": "Snap",
        "Text": "New Snap"
    },
    {
        "Sender": "User45",
        "idNotify": "Notify3Request",
        "Cat": "Request",
        "Text": "New Request"
    },
    {
        "Sender": "User41",
        "idNotify": "Notify4Snap",
        "Cat": "Snap",
        "Text": "New Snap"
    },
    {
        "Sender": "User95",
        "idNotify": "Notify5Message",
        "Cat": "Message",
        "Text": "New Message"
    },
    {
        "Sender": "User94",
        "idNotify": "Notify6Message",
        "Cat": "Message",
        "Text": "New Message"
    },
    {
        "Sender": "User75",
        "idNotify": "Notify7Request",
        "Cat": "Request",
        "Text": "New Request"
    },
    {
        "Sender": "User26",
        "idNotify": "Notify8Request",
        "Cat": "Request",
        "Text": "New Request"
    },
    {
        "Sender": "User18",
        "idNotify": "Notify9Request",
        "Cat": "Request",
        "Text": "New Request"
    },
    {
        "Sender": "User88",
        "idNotify": "Notify0Message",
        "Cat": "Message",
        "Text": "New Message"
    },
    {
        "Sender": "User3",
        "idNotify": "Notify1Snap",
        "Cat": "Snap",
        "Text": "New Snap"
    },
    {
        "Sender": "User13",
        "idNotify": "Notify2Message",
        "Cat": "Message",
        "Text": "New Message"
    },
    {
        "Sender": "User39",
        "idNotify": "Notify3Message",
        "Cat": "Message",
        "Text": "New Message"
    },
    {
        "Sender": "User32",
        "idNotify": "Notify4Snap",
        "Cat": "Snap",
        "Text": "New Snap"
    },
    {
        "Sender": "User56",
        "idNotify": "Notify5Snap",
        "Cat": "Snap",
        "Text": "New Snap"
    },
    {
        "Sender": "User49",
        "idNotify": "Notify6Message",
        "Cat": "Message",
        "Text": "New Message"
    },
    {
        "Sender": "User12",
        "idNotify": "Notify7Request",
        "Cat": "Request",
        "Text": "New Request"
    },
    {
        "Sender": "User39",
        "idNotify": "Notify8Message",
        "Cat": "Message",
        "Text": "New Message"
    },
    {
        "Sender": "User54",
        "idNotify": "Notify0Request",
        "Cat": "Request",
        "Text": "New Request"
    },
    {
        "Sender": "User37",
        "idNotify": "Notify1Request",
        "Cat": "Request",
        "Text": "New Request"
    },
    {
        "Sender": "User24",
        "idNotify": "Notify2Message",
        "Cat": "Message",
        "Text": "New Message"
    },
    {
        "Sender": "User45",
        "idNotify": "Notify3Request",
        "Cat": "Request",
        "Text": "New Request"
    },
    {
        "Sender": "User17",
        "idNotify": "Notify4Message",
        "Cat": "Message",
        "Text": "New Message"
    },
    {
        "Sender": "User76",
        "idNotify": "Notify5Snap",
        "Cat": "Snap",
        "Text": "New Snap"
    },
    {
        "Sender": "User53",
        "idNotify": "Notify0Request",
        "Cat": "Request",
        "Text": "New Request"
    },
    {
        "Sender": "User73",
        "idNotify": "Notify0Message",
        "Cat": "Message",
        "Text": "New Message"
    },
    {
        "Sender": "User57",
        "idNotify": "Notify1Request",
        "Cat": "Request",
        "Text": "New Request"
    },
    {
        "Sender": "User6",
        "idNotify": "Notify2Message",
        "Cat": "Message",
        "Text": "New Message"
    },
    {
        "Sender": "User55",
        "idNotify": "Notify3Request",
        "Cat": "Request",
        "Text": "New Request"
    },
    {
        "Sender": "User33",
        "idNotify": "Notify4Request",
        "Cat": "Request",
        "Text": "New Request"
    },
    {
        "Sender": "User48",
        "idNotify": "Notify5Snap",
        "Cat": "Snap",
        "Text": "New Snap"
    },
    {
        "Sender": "User16",
        "idNotify": "Notify6Snap",
        "Cat": "Snap",
        "Text": "New Snap"
    },
    {
        "Sender": "User66",
        "idNotify": "Notify0Request",
        "Cat": "Request",
        "Text": "New Request"
    },
    {
        "Sender": "User41",
        "idNotify": "Notify1Message",
        "Cat": "Message",
        "Text": "New Message"
    },
    {
        "Sender": "User61",
        "idNotify": "Notify2Snap",
        "Cat": "Snap",
        "Text": "New Snap"
    },
    {
        "Sender": "User61",
        "idNotify": "Notify3Snap",
        "Cat": "Snap",
        "Text": "New Snap"
    },
    {
        "Sender": "User31",
        "idNotify": "Notify4Request",
        "Cat": "Request",
        "Text": "New Request"
    },
    {
        "Sender": "User83",
        "idNotify": "Notify0Message",
        "Cat": "Message",
        "Text": "New Message"
    },
    {
        "Sender": "User21",
        "idNotify": "Notify1Message",
        "Cat": "Message",
        "Text": "New Message"
    },
    {
        "Sender": "User47",
        "idNotify": "Notify2Message",
        "Cat": "Message",
        "Text": "New Message"
    },
    {
        "Sender": "User4",
        "idNotify": "Notify3Message",
        "Cat": "Message",
        "Text": "New Message"
    },
    {
        "Sender": "User0",
        "idNotify": "Notify4Message",
        "Cat": "Message",
        "Text": "New Message"
    },
    {
        "Sender": "User84",
        "idNotify": "Notify5Snap",
        "Cat": "Snap",
        "Text": "New Snap"
    },
    {
        "Sender": "User69",
        "idNotify": "Notify0Snap",
        "Cat": "Snap",
        "Text": "New Snap"
    },
    {
        "Sender": "User88",
        "idNotify": "Notify0Request",
        "Cat": "Request",
        "Text": "New Request"
    },
    {
        "Sender": "User27",
        "idNotify": "Notify1Request",
        "Cat": "Request",
        "Text": "New Request"
    },
    {
        "Sender": "User71",
        "idNotify": "Notify2Snap",
        "Cat": "Snap",
        "Text": "New Snap"
    },
    {
        "Sender": "User11",
        "idNotify": "Notify0Snap",
        "Cat": "Snap",
        "Text": "New Snap"
    },
    {
        "Sender": "User52",
        "idNotify": "Notify1Message",
        "Cat": "Message",
        "Text": "New Message"
    },
    {
        "Sender": "User75",
        "idNotify": "Notify2Request",
        "Cat": "Request",
        "Text": "New Request"
    },
    {
        "Sender": "User63",
        "idNotify": "Notify3Message",
        "Cat": "Message",
        "Text": "New Message"
    },
    {
        "Sender": "User99",
        "idNotify": "Notify4Request",
        "Cat": "Request",
        "Text": "New Request"
    },
    {
        "Sender": "User46",
        "idNotify": "Notify5Snap",
        "Cat": "Snap",
        "Text": "New Snap"
    },
    {
        "Sender": "User62",
        "idNotify": "Notify6Request",
        "Cat": "Request",
        "Text": "New Request"
    },
    {
        "Sender": "User25",
        "idNotify": "Notify0Request",
        "Cat": "Request",
        "Text": "New Request"
    },
    {
        "Sender": "User95",
        "idNotify": "Notify1Request",
        "Cat": "Request",
        "Text": "New Request"
    },
    {
        "Sender": "User44",
        "idNotify": "Notify2Request",
        "Cat": "Request",
        "Text": "New Request"
    },
    {
        "Sender": "User62",
        "idNotify": "Notify3Message",
        "Cat": "Message",
        "Text": "New Message"
    },
    {
        "Sender": "User68",
        "idNotify": "Notify0Request",
        "Cat": "Request",
        "Text": "New Request"
    },
    {
        "Sender": "User2",
        "idNotify": "Notify1Snap",
        "Cat": "Snap",
        "Text": "New Snap"
    },
    {
        "Sender": "User49",
        "idNotify": "Notify0Snap",
        "Cat": "Snap",
        "Text": "New Snap"
    },
    {
        "Sender": "User64",
        "idNotify": "Notify1Request",
        "Cat": "Request",
        "Text": "New Request"
    },
    {
        "Sender": "User10",
        "idNotify": "Notify2Message",
        "Cat": "Message",
        "Text": "New Message"
    },
    {
        "Sender": "User42",
        "idNotify": "Notify3Message",
        "Cat": "Message",
        "Text": "New Message"
    },
    {
        "Sender": "User38",
        "idNotify": "Notify4Snap",
        "Cat": "Snap",
        "Text": "New Snap"
    },
    {
        "Sender": "User75",
        "idNotify": "Notify0Snap",
        "Cat": "Snap",
        "Text": "New Snap"
    },
    {
        "Sender": "User19",
        "idNotify": "Notify1Snap",
        "Cat": "Snap",
        "Text": "New Snap"
    },
    {
        "Sender": "User72",
        "idNotify": "Notify2Request",
        "Cat": "Request",
        "Text": "New Request"
    },
    {
        "Sender": "User13",
        "idNotify": "Notify0Snap",
        "Cat": "Snap",
        "Text": "New Snap"
    },
    {
        "Sender": "User8",
        "idNotify": "Notify1Snap",
        "Cat": "Snap",
        "Text": "New Snap"
    },
    {
        "Sender": "User55",
        "idNotify": "Notify2Message",
        "Cat": "Message",
        "Text": "New Message"
    },
    {
        "Sender": "User85",
        "idNotify": "Notify3Request",
        "Cat": "Request",
        "Text": "New Request"
    },
    {
        "Sender": "User36",
        "idNotify": "Notify4Message",
        "Cat": "Message",
        "Text": "New Message"
    },
    {
        "Sender": "User32",
        "idNotify": "Notify5Message",
        "Cat": "Message",
        "Text": "New Message"
    },
    {
        "Sender": "User55",
        "idNotify": "Notify0Message",
        "Cat": "Message",
        "Text": "New Message"
    },
    {
        "Sender": "User15",
        "idNotify": "Notify1Message",
        "Cat": "Message",
        "Text": "New Message"
    },
    {
        "Sender": "User44",
        "idNotify": "Notify2Request",
        "Cat": "Request",
        "Text": "New Request"
    },
    {
        "Sender": "User3",
        "idNotify": "Notify3Message",
        "Cat": "Message",
        "Text": "New Message"
    },
    {
        "Sender": "User28",
        "idNotify": "Notify4Request",
        "Cat": "Request",
        "Text": "New Request"
    },
    {
        "Sender": "User22",
        "idNotify": "Notify5Snap",
        "Cat": "Snap",
        "Text": "New Snap"
    },
    {
        "Sender": "User78",
        "idNotify": "Notify0Snap",
        "Cat": "Snap",
        "Text": "New Snap"
    },
    {
        "Sender": "User53",
        "idNotify": "Notify1Request",
        "Cat": "Request",
        "Text": "New Request"
    },
    {
        "Sender": "User17",
        "idNotify": "Notify2Message",
        "Cat": "Message",
        "Text": "New Message"
    },
    {
        "Sender": "User89",
        "idNotify": "Notify0Message",
        "Cat": "Message",
        "Text": "New Message"
    },
    {
        "Sender": "User10",
        "idNotify": "Notify0Request",
        "Cat": "Request",
        "Text": "New Request"
    },
    {
        "Sender": "User7",
        "idNotify": "Notify1Message",
        "Cat": "Message",
        "Text": "New Message"
    },
    {
        "Sender": "User41",
        "idNotify": "Notify2Request",
        "Cat": "Request",
        "Text": "New Request"
    },
    {
        "Sender": "User11",
        "idNotify": "Notify3Message",
        "Cat": "Message",
        "Text": "New Message"
    },
    {
        "Sender": "User7",
        "idNotify": "Notify4Snap",
        "Cat": "Snap",
        "Text": "New Snap"
    },
    {
        "Sender": "User30",
        "idNotify": "Notify5Snap",
        "Cat": "Snap",
        "Text": "New Snap"
    },
    {
        "Sender": "User91",
        "idNotify": "Notify6Message",
        "Cat": "Message",
        "Text": "New Message"
    },
    {
        "Sender": "User78",
        "idNotify": "Notify0Message",
        "Cat": "Message",
        "Text": "New Message"
    },
    {
        "Sender": "User5",
        "idNotify": "Notify1Request",
        "Cat": "Request",
        "Text": "New Request"
    },
    {
        "Sender": "User64",
        "idNotify": "Notify2Request",
        "Cat": "Request",
        "Text": "New Request"
    },
    {
        "Sender": "User30",
        "idNotify": "Notify3Snap",
        "Cat": "Snap",
        "Text": "New Snap"
    },
    {
        "Sender": "User71",
        "idNotify": "Notify4Message",
        "Cat": "Message",
        "Text": "New Message"
    },
    {
        "Sender": "User3",
        "idNotify": "Notify5Request",
        "Cat": "Request",
        "Text": "New Request"
    },
    {
        "Sender": "User82",
        "idNotify": "Notify0Request",
        "Cat": "Request",
        "Text": "New Request"
    },
    {
        "Sender": "User86",
        "idNotify": "Notify1Request",
        "Cat": "Request",
        "Text": "New Request"
    },
    {
        "Sender": "User18",
        "idNotify": "Notify2Request",
        "Cat": "Request",
        "Text": "New Request"
    },
    {
        "Sender": "User30",
        "idNotify": "Notify3Request",
        "Cat": "Request",
        "Text": "New Request"
    },
    {
        "Sender": "User90",
        "idNotify": "Notify4Snap",
        "Cat": "Snap",
        "Text": "New Snap"
    },
    {
        "Sender": "User18",
        "idNotify": "Notify5Message",
        "Cat": "Message",
        "Text": "New Message"
    },
    {
        "Sender": "User6",
        "idNotify": "Notify0Snap",
        "Cat": "Snap",
        "Text": "New Snap"
    },
    {
        "Sender": "User34",
        "idNotify": "Notify1Request",
        "Cat": "Request",
        "Text": "New Request"
    },
    {
        "Sender": "User84",
        "idNotify": "Notify2Request",
        "Cat": "Request",
        "Text": "New Request"
    },
    {
        "Sender": "User66",
        "idNotify": "Notify3Request",
        "Cat": "Request",
        "Text": "New Request"
    },
    {
        "Sender": "User48",
        "idNotify": "Notify4Message",
        "Cat": "Message",
        "Text": "New Message"
    },
    {
        "Sender": "User95",
        "idNotify": "Notify5Request",
        "Cat": "Request",
        "Text": "New Request"
    },
    {
        "Sender": "User43",
        "idNotify": "Notify6Message",
        "Cat": "Message",
        "Text": "New Message"
    },
    {
        "Sender": "User89",
        "idNotify": "Notify7Message",
        "Cat": "Message",
        "Text": "New Message"
    },
    {
        "Sender": "User82",
        "idNotify": "Notify8Request",
        "Cat": "Request",
        "Text": "New Request"
    },
    {
        "Sender": "User23",
        "idNotify": "Notify0Message",
        "Cat": "Message",
        "Text": "New Message"
    },
    {
        "Sender": "User65",
        "idNotify": "Notify1Snap",
        "Cat": "Snap",
        "Text": "New Snap"
    },
    {
        "Sender": "User36",
        "idNotify": "Notify2Message",
        "Cat": "Message",
        "Text": "New Message"
    },
    {
        "Sender": "User44",
        "idNotify": "Notify3Request",
        "Cat": "Request",
        "Text": "New Request"
    },
    {
        "Sender": "User46",
        "idNotify": "Notify4Snap",
        "Cat": "Snap",
        "Text": "New Snap"
    },
    {
        "Sender": "User34",
        "idNotify": "Notify5Snap",
        "Cat": "Snap",
        "Text": "New Snap"
    },
    {
        "Sender": "User88",
        "idNotify": "Notify6Message",
        "Cat": "Message",
        "Text": "New Message"
    },
    {
        "Sender": "User76",
        "idNotify": "Notify0Message",
        "Cat": "Message",
        "Text": "New Message"
    },
    {
        "Sender": "User85",
        "idNotify": "Notify1Request",
        "Cat": "Request",
        "Text": "New Request"
    },
    {
        "Sender": "User73",
        "idNotify": "Notify2Snap",
        "Cat": "Snap",
        "Text": "New Snap"
    },
    {
        "Sender": "User74",
        "idNotify": "Notify3Request",
        "Cat": "Request",
        "Text": "New Request"
    },
    {
        "Sender": "User33",
        "idNotify": "Notify4Snap",
        "Cat": "Snap",
        "Text": "New Snap"
    },
    {
        "Sender": "User70",
        "idNotify": "Notify5Snap",
        "Cat": "Snap",
        "Text": "New Snap"
    },
    {
        "Sender": "User67",
        "idNotify": "Notify6Message",
        "Cat": "Message",
        "Text": "New Message"
    },
    {
        "Sender": "User51",
        "idNotify": "Notify7Message",
        "Cat": "Message",
        "Text": "New Message"
    },
    {
        "Sender": "User62",
        "idNotify": "Notify0Message",
        "Cat": "Message",
        "Text": "New Message"
    },
    {
        "Sender": "User62",
        "idNotify": "Notify1Request",
        "Cat": "Request",
        "Text": "New Request"
    },
    {
        "Sender": "User69",
        "idNotify": "Notify2Request",
        "Cat": "Request",
        "Text": "New Request"
    },
    {
        "Sender": "User57",
        "idNotify": "Notify3Snap",
        "Cat": "Snap",
        "Text": "New Snap"
    },
    {
        "Sender": "User75",
        "idNotify": "Notify0Message",
        "Cat": "Message",
        "Text": "New Message"
    },
    {
        "Sender": "User97",
        "idNotify": "Notify1Request",
        "Cat": "Request",
        "Text": "New Request"
    },
    {
        "Sender": "User19",
        "idNotify": "Notify2Snap",
        "Cat": "Snap",
        "Text": "New Snap"
    },
    {
        "Sender": "User19",
        "idNotify": "Notify3Snap",
        "Cat": "Snap",
        "Text": "New Snap"
    },
    {
        "Sender": "User50",
        "idNotify": "Notify0Snap",
        "Cat": "Snap",
        "Text": "New Snap"
    },
    {
        "Sender": "User65",
        "idNotify": "Notify1Snap",
        "Cat": "Snap",
        "Text": "New Snap"
    },
    {
        "Sender": "User73",
        "idNotify": "Notify2Request",
        "Cat": "Request",
        "Text": "New Request"
    },
    {
        "Sender": "User1",
        "idNotify": "Notify3Message",
        "Cat": "Message",
        "Text": "New Message"
    },
    {
        "Sender": "User3",
        "idNotify": "Notify4Request",
        "Cat": "Request",
        "Text": "New Request"
    },
    {
        "Sender": "User17",
        "idNotify": "Notify5Request",
        "Cat": "Request",
        "Text": "New Request"
    },
    {
        "Sender": "User9",
        "idNotify": "Notify6Snap",
        "Cat": "Snap",
        "Text": "New Snap"
    },
    {
        "Sender": "User13",
        "idNotify": "Notify7Snap",
        "Cat": "Snap",
        "Text": "New Snap"
    },
    {
        "Sender": "User50",
        "idNotify": "Notify0Message",
        "Cat": "Message",
        "Text": "New Message"
    },
    {
        "Sender": "User83",
        "idNotify": "Notify1Request",
        "Cat": "Request",
        "Text": "New Request"
    },
    {
        "Sender": "User46",
        "idNotify": "Notify2Message",
        "Cat": "Message",
        "Text": "New Message"
    },
    {
        "Sender": "User13",
        "idNotify": "Notify3Request",
        "Cat": "Request",
        "Text": "New Request"
    },
    {
        "Sender": "User99",
        "idNotify": "Notify4Request",
        "Cat": "Request",
        "Text": "New Request"
    },
    {
        "Sender": "User39",
        "idNotify": "Notify5Message",
        "Cat": "Message",
        "Text": "New Message"
    },
    {
        "Sender": "User77",
        "idNotify": "Notify6Snap",
        "Cat": "Snap",
        "Text": "New Snap"
    },
    {
        "Sender": "User77",
        "idNotify": "Notify7Snap",
        "Cat": "Snap",
        "Text": "New Snap"
    },
    {
        "Sender": "User74",
        "idNotify": "Notify8Request",
        "Cat": "Request",
        "Text": "New Request"
    },
    {
        "Sender": "User52",
        "idNotify": "Notify9Snap",
        "Cat": "Snap",
        "Text": "New Snap"
    },
    {
        "Sender": "User26",
        "idNotify": "Notify0Message",
        "Cat": "Message",
        "Text": "New Message"
    },
    {
        "Sender": "User77",
        "idNotify": "Notify1Snap",
        "Cat": "Snap",
        "Text": "New Snap"
    },
    {
        "Sender": "User17",
        "idNotify": "Notify2Request",
        "Cat": "Request",
        "Text": "New Request"
    },
    {
        "Sender": "User72",
        "idNotify": "Notify3Request",
        "Cat": "Request",
        "Text": "New Request"
    },
    {
        "Sender": "User39",
        "idNotify": "Notify4Snap",
        "Cat": "Snap",
        "Text": "New Snap"
    },
    {
        "Sender": "User61",
        "idNotify": "Notify5Message",
        "Cat": "Message",
        "Text": "New Message"
    },
    {
        "Sender": "User60",
        "idNotify": "Notify6Snap",
        "Cat": "Snap",
        "Text": "New Snap"
    },
    {
        "Sender": "User3",
        "idNotify": "Notify7Request",
        "Cat": "Request",
        "Text": "New Request"
    },
    {
        "Sender": "User11",
        "idNotify": "Notify8Request",
        "Cat": "Request",
        "Text": "New Request"
    },
    {
        "Sender": "User97",
        "idNotify": "Notify0Snap",
        "Cat": "Snap",
        "Text": "New Snap"
    },
    {
        "Sender": "User32",
        "idNotify": "Notify1Request",
        "Cat": "Request",
        "Text": "New Request"
    },
    {
        "Sender": "User41",
        "idNotify": "Notify2Message",
        "Cat": "Message",
        "Text": "New Message"
    },
    {
        "Sender": "User65",
        "idNotify": "Notify3Request",
        "Cat": "Request",
        "Text": "New Request"
    },
    {
        "Sender": "User42",
        "idNotify": "Notify4Request",
        "Cat": "Request",
        "Text": "New Request"
    },
    {
        "Sender": "User56",
        "idNotify": "Notify5Request",
        "Cat": "Request",
        "Text": "New Request"
    },
    {
        "Sender": "User63",
        "idNotify": "Notify0Request",
        "Cat": "Request",
        "Text": "New Request"
    },
    {
        "Sender": "User31",
        "idNotify": "Notify1Message",
        "Cat": "Message",
        "Text": "New Message"
    },
    {
        "Sender": "User54",
        "idNotify": "Notify2Message",
        "Cat": "Message",
        "Text": "New Message"
    },
    {
        "Sender": "User58",
        "idNotify": "Notify3Request",
        "Cat": "Request",
        "Text": "New Request"
    },
    {
        "Sender": "User31",
        "idNotify": "Notify4Snap",
        "Cat": "Snap",
        "Text": "New Snap"
    },
    {
        "Sender": "User53",
        "idNotify": "Notify5Message",
        "Cat": "Message",
        "Text": "New Message"
    },
    {
        "Sender": "User94",
        "idNotify": "Notify6Message",
        "Cat": "Message",
        "Text": "New Message"
    },
    {
        "Sender": "User10",
        "idNotify": "Notify7Snap",
        "Cat": "Snap",
        "Text": "New Snap"
    },
    {
        "Sender": "User88",
        "idNotify": "Notify8Message",
        "Cat": "Message",
        "Text": "New Message"
    },
    {
        "Sender": "User36",
        "idNotify": "Notify9Request",
        "Cat": "Request",
        "Text": "New Request"
    },
    {
        "Sender": "User61",
        "idNotify": "Notify0Snap",
        "Cat": "Snap",
        "Text": "New Snap"
    },
    {
        "Sender": "User16",
        "idNotify": "Notify1Snap",
        "Cat": "Snap",
        "Text": "New Snap"
    },
    {
        "Sender": "User26",
        "idNotify": "Notify0Message",
        "Cat": "Message",
        "Text": "New Message"
    },
    {
        "Sender": "User40",
        "idNotify": "Notify1Request",
        "Cat": "Request",
        "Text": "New Request"
    },
    {
        "Sender": "User75",
        "idNotify": "Notify2Snap",
        "Cat": "Snap",
        "Text": "New Snap"
    },
    {
        "Sender": "User69",
        "idNotify": "Notify3Request",
        "Cat": "Request",
        "Text": "New Request"
    },
    {
        "Sender": "User97",
        "idNotify": "Notify4Snap",
        "Cat": "Snap",
        "Text": "New Snap"
    },
    {
        "Sender": "User87",
        "idNotify": "Notify5Snap",
        "Cat": "Snap",
        "Text": "New Snap"
    },
    {
        "Sender": "User2",
        "idNotify": "Notify6Snap",
        "Cat": "Snap",
        "Text": "New Snap"
    },
    {
        "Sender": "User85",
        "idNotify": "Notify0Request",
        "Cat": "Request",
        "Text": "New Request"
    },
    {
        "Sender": "User82",
        "idNotify": "Notify1Request",
        "Cat": "Request",
        "Text": "New Request"
    },
    {
        "Sender": "User84",
        "idNotify": "Notify2Message",
        "Cat": "Message",
        "Text": "New Message"
    },
    {
        "Sender": "User17",
        "idNotify": "Notify3Request",
        "Cat": "Request",
        "Text": "New Request"
    },
    {
        "Sender": "User5",
        "idNotify": "Notify4Message",
        "Cat": "Message",
        "Text": "New Message"
    },
    {
        "Sender": "User0",
        "idNotify": "Notify5Message",
        "Cat": "Message",
        "Text": "New Message"
    },
    {
        "Sender": "User96",
        "idNotify": "Notify0Message",
        "Cat": "Message",
        "Text": "New Message"
    },
    {
        "Sender": "User62",
        "idNotify": "Notify1Message",
        "Cat": "Message",
        "Text": "New Message"
    },
    {
        "Sender": "User94",
        "idNotify": "Notify2Message",
        "Cat": "Message",
        "Text": "New Message"
    },
    {
        "Sender": "User83",
        "idNotify": "Notify3Message",
        "Cat": "Message",
        "Text": "New Message"
    },
    {
        "Sender": "User3",
        "idNotify": "Notify4Message",
        "Cat": "Message",
        "Text": "New Message"
    },
    {
        "Sender": "User80",
        "idNotify": "Notify5Snap",
        "Cat": "Snap",
        "Text": "New Snap"
    },
    {
        "Sender": "User50",
        "idNotify": "Notify6Request",
        "Cat": "Request",
        "Text": "New Request"
    },
    {
        "Sender": "User1",
        "idNotify": "Notify0Request",
        "Cat": "Request",
        "Text": "New Request"
    },
    {
        "Sender": "User47",
        "idNotify": "Notify1Message",
        "Cat": "Message",
        "Text": "New Message"
    },
    {
        "Sender": "User76",
        "idNotify": "Notify2Request",
        "Cat": "Request",
        "Text": "New Request"
    },
    {
        "Sender": "User3",
        "idNotify": "Notify3Message",
        "Cat": "Message",
        "Text": "New Message"
    },
    {
        "Sender": "User45",
        "idNotify": "Notify4Snap",
        "Cat": "Snap",
        "Text": "New Snap"
    },
    {
        "Sender": "User32",
        "idNotify": "Notify5Message",
        "Cat": "Message",
        "Text": "New Message"
    },
    {
        "Sender": "User26",
        "idNotify": "Notify6Snap",
        "Cat": "Snap",
        "Text": "New Snap"
    },
    {
        "Sender": "User66",
        "idNotify": "Notify7Message",
        "Cat": "Message",
        "Text": "New Message"
    },
    {
        "Sender": "User84",
        "idNotify": "Notify8Snap",
        "Cat": "Snap",
        "Text": "New Snap"
    },
    {
        "Sender": "User43",
        "idNotify": "Notify9Request",
        "Cat": "Request",
        "Text": "New Request"
    },
    {
        "Sender": "User97",
        "idNotify": "Notify0Snap",
        "Cat": "Snap",
        "Text": "New Snap"
    },
    {
        "Sender": "User45",
        "idNotify": "Notify1Request",
        "Cat": "Request",
        "Text": "New Request"
    },
    {
        "Sender": "User17",
        "idNotify": "Notify2Message",
        "Cat": "Message",
        "Text": "New Message"
    },
    {
        "Sender": "User42",
        "idNotify": "Notify3Snap",
        "Cat": "Snap",
        "Text": "New Snap"
    },
    {
        "Sender": "User34",
        "idNotify": "Notify4Request",
        "Cat": "Request",
        "Text": "New Request"
    },
    {
        "Sender": "User39",
        "idNotify": "Notify0Request",
        "Cat": "Request",
        "Text": "New Request"
    },
    {
        "Sender": "User27",
        "idNotify": "Notify0Request",
        "Cat": "Request",
        "Text": "New Request"
    },
    {
        "Sender": "User19",
        "idNotify": "Notify1Message",
        "Cat": "Message",
        "Text": "New Message"
    },
    {
        "Sender": "User73",
        "idNotify": "Notify2Request",
        "Cat": "Request",
        "Text": "New Request"
    },
    {
        "Sender": "User40",
        "idNotify": "Notify3Snap",
        "Cat": "Snap",
        "Text": "New Snap"
    },
    {
        "Sender": "User21",
        "idNotify": "Notify4Message",
        "Cat": "Message",
        "Text": "New Message"
    },
    {
        "Sender": "User92",
        "idNotify": "Notify5Snap",
        "Cat": "Snap",
        "Text": "New Snap"
    },
    {
        "Sender": "User60",
        "idNotify": "Notify6Snap",
        "Cat": "Snap",
        "Text": "New Snap"
    },
    {
        "Sender": "User17",
        "idNotify": "Notify7Message",
        "Cat": "Message",
        "Text": "New Message"
    },
    {
        "Sender": "User22",
        "idNotify": "Notify0Snap",
        "Cat": "Snap",
        "Text": "New Snap"
    },
    {
        "Sender": "User15",
        "idNotify": "Notify1Snap",
        "Cat": "Snap",
        "Text": "New Snap"
    },
    {
        "Sender": "User61",
        "idNotify": "Notify2Snap",
        "Cat": "Snap",
        "Text": "New Snap"
    },
    {
        "Sender": "User88",
        "idNotify": "Notify3Message",
        "Cat": "Message",
        "Text": "New Message"
    },
    {
        "Sender": "User3",
        "idNotify": "Notify4Message",
        "Cat": "Message",
        "Text": "New Message"
    },
    {
        "Sender": "User26",
        "idNotify": "Notify5Snap",
        "Cat": "Snap",
        "Text": "New Snap"
    },
    {
        "Sender": "User6",
        "idNotify": "Notify6Request",
        "Cat": "Request",
        "Text": "New Request"
    },
    {
        "Sender": "User28",
        "idNotify": "Notify7Request",
        "Cat": "Request",
        "Text": "New Request"
    },
    {
        "Sender": "User14",
        "idNotify": "Notify8Message",
        "Cat": "Message",
        "Text": "New Message"
    }
]